secrets/__init__.py
secrets/config.py
secrets/generator.py
secrets/password.py
secrets-1.0.2.data/scripts/gpgcat
secrets-1.0.2.data/scripts/otpcalendar
secrets-1.0.2.data/scripts/request-encode
secrets-1.0.2.data/scripts/secrets-config
secrets-1.0.2.data/scripts/secrets-passwd
secrets-1.0.2.data/scripts/secrets-password-trainer
secrets-1.0.2.data/scripts/secrets-pwgen
secrets-1.0.2.dist-info/METADATA
secrets-1.0.2.dist-info/WHEEL
secrets-1.0.2.dist-info/top_level.txt
secrets-1.0.2.dist-info/RECORD
