Metadata-Version: 1.0
Name: secrets
Version: 1.0.2
Summary: Scripts to manage LDAP users and change LDAP passwords
Home-page: http://tuohela.net/packages/secrets
Author: Ilkka Tuohela
Author-email: hile@iki.fi
License: PSF
Keywords: LDAP server password change user management
Platform: UNKNOWN
